claravid/__init__.py
claravid/dataset.py
claravid/io_utils.py
claravid/scene_complexity_profile.py
claravid-0.2.0.dist-info/METADATA
claravid-0.2.0.dist-info/WHEEL
claravid-0.2.0.dist-info/licenses/LICENSE
claravid-0.2.0.dist-info/RECORD
