Metadata-Version: 2.4
Name: claravid
Version: 0.2.0
Summary: Utilities for handling ClaraVid dataset
Project-URL: Homepage, https://github.com/rdbch/claravid_code
Author-email: Radu Beche <radu.beche@cs.utcluj.ro>
License-Expression: MIT
License-File: LICENSE
Requires-Python: >=3.9
Requires-Dist: numpy
Requires-Dist: pillow
Provides-Extra: all
Requires-Dist: jupyterlab; extra == 'all'
Requires-Dist: matplotlib; extra == 'all'
Requires-Dist: open3d; extra == 'all'
Requires-Dist: opencv-python; extra == 'all'
Requires-Dist: scikit-image; extra == 'all'
Requires-Dist: scipy; extra == 'all'
Requires-Dist: seaborn; extra == 'all'
Requires-Dist: tqdm; extra == 'all'
Provides-Extra: dsp
Requires-Dist: matplotlib; extra == 'dsp'
Requires-Dist: opencv-python; extra == 'dsp'
Requires-Dist: scikit-image; extra == 'dsp'
Requires-Dist: scipy; extra == 'dsp'
Requires-Dist: seaborn; extra == 'dsp'
Requires-Dist: tqdm; extra == 'dsp'
